edsteva/__init__.py
edsteva/io/__init__.py
edsteva/io/files.py
edsteva/io/hive.py
edsteva/io/i2b2_mapping.py
edsteva/io/postgres.py
edsteva/io/settings.py
edsteva/io/synthetic/__init__.py
edsteva/io/synthetic/biology.py
edsteva/io/synthetic/care_site.py
edsteva/io/synthetic/note.py
edsteva/io/synthetic/synthetic.py
edsteva/io/synthetic/utils.py
edsteva/io/synthetic/visit.py
edsteva/metrics/__init__.py
edsteva/metrics/error.py
edsteva/metrics/error_after_t0.py
edsteva/metrics/error_between_t0_t1.py
edsteva/models/__init__.py
edsteva/models/base.py
edsteva/models/rectangle_function/__init__.py
edsteva/models/rectangle_function/algos/__init__.py
edsteva/models/rectangle_function/algos/loss_minimization.py
edsteva/models/rectangle_function/rectangle_function.py
edsteva/models/rectangle_function/viz_configs/__init__.py
edsteva/models/rectangle_function/viz_configs/defaults.py
edsteva/models/rectangle_function/viz_configs/normalized_probe_dashboard.py
edsteva/models/rectangle_function/viz_configs/normalized_probe_plot.py
edsteva/models/rectangle_function/viz_configs/probe_dashboard.py
edsteva/models/rectangle_function/viz_configs/probe_plot.py
edsteva/models/step_function/__init__.py
edsteva/models/step_function/algos/__init__.py
edsteva/models/step_function/algos/loss_minimization.py
edsteva/models/step_function/algos/quantile.py
edsteva/models/step_function/step_function.py
edsteva/models/step_function/viz_configs/__init__.py
edsteva/models/step_function/viz_configs/defaults.py
edsteva/models/step_function/viz_configs/normalized_probe_dashboard.py
edsteva/models/step_function/viz_configs/normalized_probe_plot.py
edsteva/models/step_function/viz_configs/probe_dashboard.py
edsteva/models/step_function/viz_configs/probe_plot.py
edsteva/probes/__init__.py
edsteva/probes/base/__init__.py
edsteva/probes/base/base.py
edsteva/probes/base/viz_configs.py
edsteva/probes/biology/__init__.py
edsteva/probes/biology/biology.py
edsteva-0.2.8.dist-info/WHEEL
edsteva-0.2.8.dist-info/LICENSE
edsteva-0.2.8.dist-info/METADATA
edsteva-0.2.8.dist-info/RECORD
