Metadata-Version: 2.1
Name: edsteva
Version: 0.2.8
Summary: EDS-TeVa provides a set of tools that aims at modeling the adoption over time and across space of the Electronic Health Records.
Home-page: https://github.com/aphp/edsteva
License: BSD 3-Clause
Keywords: OMOP,Data Analysis,Electronic health record
Author: Adam Remaki
Author-email: adam.remaki@aphp.fr
Maintainer: Adam Remaki
Maintainer-email: adam.remaki@aphp.fr
Requires-Python: >=3.7.1,<3.8.0
Classifier: Intended Audience :: Developers
Classifier: Intended Audience :: Science/Research
Classifier: License :: OSI Approved :: BSD License
Classifier: License :: Other/Proprietary License
Classifier: Operating System :: Unix
Classifier: Programming Language :: Python :: 3
Classifier: Programming Language :: Python :: 3.7
Classifier: Topic :: Scientific/Engineering
Classifier: Topic :: Software Development :: Libraries
Requires-Dist: altair (>=5.0,<6.0)
Requires-Dist: catalogue (>=2.0.8,<3.0.0)
Requires-Dist: ipython (>=7.31.0,<8.0.0)
Requires-Dist: koalas (>=1.8.2,<2.0.0)
Requires-Dist: loguru (==0.7.0)
Requires-Dist: numpy (<1.20.0)
Requires-Dist: pandas (>=1.3,<2.0)
Requires-Dist: pgpasslib (>=1.1.0,<2.0.0)
Requires-Dist: psycopg2-binary (>=2.9.3,<3.0.0)
Requires-Dist: pyarrow (>=0.10,<9.0.0)
Requires-Dist: pyspark (>=2.4.3,<2.5.0)
Requires-Dist: tqdm (>=4.65.0,<5.0.0)
Project-URL: Bug Tracker, https://github.com/aphp/edsteva/issues
Project-URL: Documentation, https://aphp.github.io/edsteva/latest/
Project-URL: Repository, https://github.com/aphp/edsteva
